GerritParser/__init__.py
GerritParser/gerritdataparser.py
gerritParse-0.6.0.dist-info/METADATA
gerritParse-0.6.0.dist-info/WHEEL
gerritParse-0.6.0.dist-info/top_level.txt
gerritParse-0.6.0.dist-info/RECORD
